AUTHORS.rst
LICENSE
MANIFEST.in
README.rst
setup.py
pathfinder/__init__.py
pathfinder/filters.py
pathfinder.egg-info/PKG-INFO
pathfinder.egg-info/SOURCES.txt
pathfinder.egg-info/dependency_links.txt
pathfinder.egg-info/top_level.txt
tests/test_pathfinder.py