Metadata-Version: 2.1
Name: pathfinder
Version: 1.0.1
Summary: pathfinder – a simpler os.walk
Home-page: http://jkeyes.github.com/pathfinder/
Author: John Keyes
Author-email: john@keyes.ie
License: MIT License
Classifier: Development Status :: 4 - Beta
Classifier: Intended Audience :: Developers
Classifier: License :: OSI Approved :: BSD License
Classifier: Operating System :: OS Independent
Classifier: Programming Language :: Python
License-File: LICENSE
License-File: AUTHORS.rst
